optics_functions/__init__.py
optics_functions/constants.py
optics_functions/coupling.py
optics_functions/rdt.py
optics_functions/utils.py
optics_functions-0.1.5.dist-info/METADATA
optics_functions-0.1.5.dist-info/WHEEL
optics_functions-0.1.5.dist-info/licenses/LICENSE
optics_functions-0.1.5.dist-info/RECORD
